{"s__Acidaminococcus fermentans": 0.6778625295177443, "s__Acidaminococcus fermentans_A": null, "s__Acidaminococcus intestini": null, "s__Acidaminococcus massiliensis": null, "s__Acidaminococcus provencensis": 0.7951836461356465, "s__Acidaminococcus sp000437815": null, "s__Acidaminococcus sp900314165": 0.7901041541282969, "s__Acidaminococcus sp900315205": null, "s__Acidaminococcus sp900538365": null, "s__Acidaminococcus sp900554515": null, "s__Acidaminococcus sp900770265": null, "s__Acidaminococcus sp902796945": null, "s__Acidaminococcus timonensis": null}